__init__.py
cli.py
gecko_yesabhishek-0.0.2.dist-info/METADATA
gecko_yesabhishek-0.0.2.dist-info/WHEEL
gecko_yesabhishek-0.0.2.dist-info/licenses/LICENSE
gecko_yesabhishek-0.0.2.dist-info/RECORD
