Metadata-Version: 2.1
Name: gecko_yesabhishek
Version: 0.0.2
Summary: Gecko is a Python library designed to streamline the process of setting up a Django application.
Author-Email: Abhishek Choudhury <choudhuryabhishek76@gmail.com>
Classifier: Programming Language :: Python :: 3
Classifier: License :: OSI Approved :: MIT License
Classifier: Operating System :: OS Independent
Project-URL: Homepage, https://github.com/pypa/gecko
Project-URL: Bug tracker, https://github.com/pypa/gecko/issues
Requires-Python: >=3.8
